LogicWeave/__init__.py
LogicWeave/exceptions.py
LogicWeave/logicweave.py
LogicWeave/logicweave_core.py
LogicWeave/transports.py
LogicWeave/web.py
LogicWeave/proto_gen/logicweave_core_pb2.py
LogicWeave/proto_gen/logicweave_pb2.py
logic_weave-0.5.5.dist-info/METADATA
logic_weave-0.5.5.dist-info/WHEEL
logic_weave-0.5.5.dist-info/top_level.txt
logic_weave-0.5.5.dist-info/RECORD
